{
  "dep_iata": "CAN",
  "arr_iata": "HKG",
  "routes": [
    {
      "airline_iata": "CX",
      "airline_icao": "CPA",
      "flight_number": "953",
      "flight_iata": "CX953",
      "dep_iata": "CAN",
      "arr_iata": "HKG",
      "dep_time": "05:00",
      "arr_time": "06:25",
      "dep_time_utc": "21:00",
      "arr_time_utc": "22:25",
      "duration": 85,
      "days": [
        "fri",
        "mon",
        "sat",
        "sun",
        "thu",
        "tue",
        "wed"
      ],
      "dep_terminal": "2",
      "arr_terminal": "1",
      "cs_airline_iata": null,
      "cs_flight_iata": null,
      "counter": 61538
    },
    {
      "airline_iata": "CX",
      "airline_icao": "CPA",
      "flight_number": "983",
      "flight_iata": "CX983",
      "dep_iata": "CAN",
      "arr_iata": "HKG",
      "dep_time": "10:10",
      "arr_time": "11:45",
      "dep_time_utc": "02:10",
      "arr_time_utc": "03:45",
      "duration": 95,
      "days": [
        "fri",
        "mon",
        "sat",
        "sun",
        "thu",
        "tue",
        "wed"
      ],
      "dep_terminal": null,
      "arr_terminal": "1",
      "cs_airline_iata": null,
      "cs_flight_iata": null,
      "counter": 103832
    },
    {
      "airline_iata": "CX",
      "airline_icao": "CPA",
      "flight_number": "989",
      "flight_iata": "CX989",
      "dep_iata": "CAN",
      "arr_iata": "HKG",
      "dep_time": "22:20",
      "arr_time": "23:40",
      "dep_time_utc": "14:20",
      "arr_time_utc": "15:40",
      "duration": 80,
      "days": [
        "fri",
        "mon",
        "sat",
        "sun",
        "thu",
        "tue",
        "wed"
      ],
      "dep_terminal": null,
      "arr_terminal": "1",
      "cs_airline_iata": null,
      "cs_flight_iata": null,
      "counter": 130522
    }
  ],
  "count": 3,
  "cached_at": 1779735240.853281
}