{
  "dep_iata": "ICN",
  "arr_iata": "CDG",
  "routes": [
    {
      "airline_iata": "AF",
      "airline_icao": "AFR",
      "flight_number": "267",
      "flight_iata": "AF267",
      "dep_iata": "ICN",
      "arr_iata": "CDG",
      "dep_time": "11:40",
      "arr_time": "18:40",
      "dep_time_utc": "02:40",
      "arr_time_utc": "16:40",
      "duration": 840,
      "days": [
        "fri",
        "mon",
        "sat",
        "sun",
        "thu",
        "tue",
        "wed"
      ],
      "dep_terminal": "2",
      "arr_terminal": "2E",
      "cs_airline_iata": null,
      "cs_flight_iata": null,
      "counter": 30143
    },
    {
      "airline_iata": "AF",
      "airline_icao": "AFR",
      "flight_number": "5093",
      "flight_iata": "AF5093",
      "dep_iata": "ICN",
      "arr_iata": "CDG",
      "dep_time": "11:20",
      "arr_time": "18:30",
      "dep_time_utc": "02:20",
      "arr_time_utc": "16:30",
      "duration": 850,
      "days": [
        "fri",
        "mon",
        "sat",
        "thu",
        "tue",
        "wed"
      ],
      "dep_terminal": "2",
      "arr_terminal": "2E",
      "cs_airline_iata": "KE",
      "cs_flight_iata": "KE901",
      "counter": 25068
    },
    {
      "airline_iata": "KE",
      "airline_icao": "KAL",
      "flight_number": "5901",
      "flight_iata": "KE5901",
      "dep_iata": "ICN",
      "arr_iata": "CDG",
      "dep_time": "11:40",
      "arr_time": "18:40",
      "dep_time_utc": "02:40",
      "arr_time_utc": "16:40",
      "duration": 840,
      "days": [
        "fri",
        "mon",
        "sun",
        "thu",
        "tue",
        "wed"
      ],
      "dep_terminal": "2",
      "arr_terminal": "2E",
      "cs_airline_iata": "AF",
      "cs_flight_iata": "AF267",
      "counter": 25740
    },
    {
      "airline_iata": "KE",
      "airline_icao": "KAL",
      "flight_number": "5903",
      "flight_iata": "KE5903",
      "dep_iata": "ICN",
      "arr_iata": "CDG",
      "dep_time": "10:05",
      "arr_time": "17:20",
      "dep_time_utc": "01:05",
      "arr_time_utc": "15:20",
      "duration": 855,
      "days": [
        "fri",
        "mon",
        "sat",
        "sun",
        "wed"
      ],
      "dep_terminal": "2",
      "arr_terminal": "1",
      "cs_airline_iata": "OZ",
      "cs_flight_iata": "OZ501",
      "counter": 18640
    },
    {
      "airline_iata": "KE",
      "airline_icao": "KAL",
      "flight_number": "901",
      "flight_iata": "KE901",
      "dep_iata": "ICN",
      "arr_iata": "CDG",
      "dep_time": "11:20",
      "arr_time": "18:30",
      "dep_time_utc": "02:20",
      "arr_time_utc": "16:30",
      "duration": 850,
      "days": [
        "fri",
        "mon",
        "sat",
        "thu",
        "tue",
        "wed"
      ],
      "dep_terminal": "2",
      "arr_terminal": "2E",
      "cs_airline_iata": null,
      "cs_flight_iata": null,
      "counter": 25068
    },
    {
      "airline_iata": "KL",
      "airline_icao": "KLM",
      "flight_number": "2345",
      "flight_iata": "KL2345",
      "dep_iata": "ICN",
      "arr_iata": "CDG",
      "dep_time": "11:40",
      "arr_time": "18:40",
      "dep_time_utc": "02:40",
      "arr_time_utc": "16:40",
      "duration": 840,
      "days": [
        "fri",
        "mon",
        "sat",
        "sun",
        "thu",
        "tue",
        "wed"
      ],
      "dep_terminal": "2",
      "arr_terminal": "2E",
      "cs_airline_iata": "AF",
      "cs_flight_iata": "AF267",
      "counter": 30143
    },
    {
      "airline_iata": "OZ",
      "airline_icao": "AAR",
      "flight_number": "501",
      "flight_iata": "OZ501",
      "dep_iata": "ICN",
      "arr_iata": "CDG",
      "dep_time": "10:05",
      "arr_time": "17:20",
      "dep_time_utc": "01:05",
      "arr_time_utc": "15:20",
      "duration": 855,
      "days": [
        "fri",
        "mon",
        "sat",
        "sun",
        "wed"
      ],
      "dep_terminal": "1",
      "arr_terminal": "1",
      "cs_airline_iata": null,
      "cs_flight_iata": null,
      "counter": 74501
    },
    {
      "airline_iata": "OZ",
      "airline_icao": "AAR",
      "flight_number": "9803",
      "flight_iata": "OZ9803",
      "dep_iata": "ICN",
      "arr_iata": "CDG",
      "dep_time": "11:20",
      "arr_time": "18:30",
      "dep_time_utc": "02:20",
      "arr_time_utc": "16:30",
      "duration": 850,
      "days": [
        "fri",
        "mon",
        "sat",
        "thu",
        "tue",
        "wed"
      ],
      "dep_terminal": "2",
      "arr_terminal": "2E",
      "cs_airline_iata": "KE",
      "cs_flight_iata": "KE901",
      "counter": 22708
    },
    {
      "airline_iata": "SK",
      "airline_icao": "SAS",
      "flight_number": "9950",
      "flight_iata": "SK9950",
      "dep_iata": "ICN",
      "arr_iata": "CDG",
      "dep_time": "11:40",
      "arr_time": "18:40",
      "dep_time_utc": "02:40",
      "arr_time_utc": "16:40",
      "duration": 840,
      "days": [
        "fri",
        "mon",
        "sat",
        "sun",
        "thu",
        "tue",
        "wed"
      ],
      "dep_terminal": "2",
      "arr_terminal": "2E",
      "cs_airline_iata": "AF",
      "cs_flight_iata": "AF267",
      "counter": 30143
    },
    {
      "airline_iata": "TW",
      "airline_icao": "TWB",
      "flight_number": "401",
      "flight_iata": "TW401",
      "dep_iata": "ICN",
      "arr_iata": "CDG",
      "dep_time": "10:10",
      "arr_time": "18:10",
      "dep_time_utc": "01:10",
      "arr_time_utc": "16:10",
      "duration": 900,
      "days": [
        "fri",
        "mon",
        "sat",
        "sun",
        "wed"
      ],
      "dep_terminal": "1",
      "arr_terminal": "1",
      "cs_airline_iata": null,
      "cs_flight_iata": null,
      "counter": 117903
    }
  ],
  "count": 10,
  "cached_at": 1779735222.382022
}