{
  "dep_iata": "JFK",
  "arr_iata": "HND",
  "routes": [
    {
      "airline_iata": "AA",
      "airline_icao": "AAL",
      "flight_number": "167",
      "flight_iata": "AA167",
      "dep_iata": "JFK",
      "arr_iata": "HND",
      "dep_time": "10:30",
      "arr_time": "13:55",
      "dep_time_utc": "14:30",
      "arr_time_utc": "04:55",
      "duration": 865,
      "days": [
        "fri",
        "mon",
        "sat",
        "sun",
        "thu",
        "tue",
        "wed"
      ],
      "dep_terminal": "8",
      "arr_terminal": "3",
      "cs_airline_iata": null,
      "cs_flight_iata": null,
      "counter": 26592
    },
    {
      "airline_iata": "AA",
      "airline_icao": "AAL",
      "flight_number": "8402",
      "flight_iata": "AA8402",
      "dep_iata": "JFK",
      "arr_iata": "HND",
      "dep_time": "13:35",
      "arr_time": "16:40",
      "dep_time_utc": "17:35",
      "arr_time_utc": "07:40",
      "duration": 845,
      "days": [
        "fri",
        "mon",
        "sat",
        "sun",
        "thu",
        "tue",
        "wed"
      ],
      "dep_terminal": "8",
      "arr_terminal": "3",
      "cs_airline_iata": "JL",
      "cs_flight_iata": "JL5",
      "counter": 13260
    },
    {
      "airline_iata": "AA",
      "airline_icao": "AAL",
      "flight_number": "8495",
      "flight_iata": "AA8495",
      "dep_iata": "JFK",
      "arr_iata": "HND",
      "dep_time": "01:30",
      "arr_time": "04:35",
      "dep_time_utc": "05:30",
      "arr_time_utc": "19:35",
      "duration": 845,
      "days": [
        "fri",
        "mon",
        "sat",
        "sun",
        "thu",
        "tue",
        "wed"
      ],
      "dep_terminal": "8",
      "arr_terminal": "3",
      "cs_airline_iata": "JL",
      "cs_flight_iata": "JL3",
      "counter": 126493
    },
    {
      "airline_iata": "JL",
      "airline_icao": "JAL",
      "flight_number": "3",
      "flight_iata": "JL3",
      "dep_iata": "JFK",
      "arr_iata": "HND",
      "dep_time": "01:30",
      "arr_time": "04:35",
      "dep_time_utc": "05:30",
      "arr_time_utc": "19:35",
      "duration": 845,
      "days": [
        "fri",
        "mon",
        "sat",
        "sun",
        "thu",
        "tue",
        "wed"
      ],
      "dep_terminal": "8",
      "arr_terminal": "3",
      "cs_airline_iata": null,
      "cs_flight_iata": null,
      "counter": 130850
    },
    {
      "airline_iata": "JL",
      "airline_icao": "JAL",
      "flight_number": "5",
      "flight_iata": "JL5",
      "dep_iata": "JFK",
      "arr_iata": "HND",
      "dep_time": "13:35",
      "arr_time": "16:40",
      "dep_time_utc": "17:35",
      "arr_time_utc": "07:40",
      "duration": 845,
      "days": [
        "fri",
        "mon",
        "sat",
        "sun",
        "thu",
        "tue",
        "wed"
      ],
      "dep_terminal": "8",
      "arr_terminal": "3",
      "cs_airline_iata": null,
      "cs_flight_iata": null,
      "counter": 13260
    },
    {
      "airline_iata": "JL",
      "airline_icao": "JAL",
      "flight_number": "7009",
      "flight_iata": "JL7009",
      "dep_iata": "JFK",
      "arr_iata": "HND",
      "dep_time": "10:30",
      "arr_time": "13:55",
      "dep_time_utc": "14:30",
      "arr_time_utc": "04:55",
      "duration": 865,
      "days": [
        "fri",
        "mon",
        "sat",
        "sun",
        "thu",
        "tue",
        "wed"
      ],
      "dep_terminal": "8",
      "arr_terminal": "3",
      "cs_airline_iata": "AA",
      "cs_flight_iata": "AA167",
      "counter": 26592
    },
    {
      "airline_iata": "LA",
      "airline_icao": "LAN",
      "flight_number": "7464",
      "flight_iata": "LA7464",
      "dep_iata": "JFK",
      "arr_iata": "HND",
      "dep_time": "13:35",
      "arr_time": "16:40",
      "dep_time_utc": "17:35",
      "arr_time_utc": "07:40",
      "duration": 845,
      "days": [
        "fri",
        "mon",
        "sat",
        "sun",
        "thu",
        "tue",
        "wed"
      ],
      "dep_terminal": "8",
      "arr_terminal": "3",
      "cs_airline_iata": "JL",
      "cs_flight_iata": "JL5",
      "counter": 13260
    },
    {
      "airline_iata": "LA",
      "airline_icao": "LAN",
      "flight_number": "7465",
      "flight_iata": "LA7465",
      "dep_iata": "JFK",
      "arr_iata": "HND",
      "dep_time": "01:30",
      "arr_time": "04:35",
      "dep_time_utc": "05:30",
      "arr_time_utc": "19:35",
      "duration": 845,
      "days": [
        "fri",
        "mon",
        "sat",
        "sun",
        "thu",
        "tue",
        "wed"
      ],
      "dep_terminal": "8",
      "arr_terminal": "3",
      "cs_airline_iata": "JL",
      "cs_flight_iata": "JL3",
      "counter": 125935
    },
    {
      "airline_iata": "MH",
      "airline_icao": "MAS",
      "flight_number": "9103",
      "flight_iata": "MH9103",
      "dep_iata": "JFK",
      "arr_iata": "HND",
      "dep_time": "01:30",
      "arr_time": "04:35",
      "dep_time_utc": "05:30",
      "arr_time_utc": "19:35",
      "duration": 845,
      "days": [
        "fri",
        "mon",
        "sat",
        "sun",
        "thu",
        "tue",
        "wed"
      ],
      "dep_terminal": "8",
      "arr_terminal": "3",
      "cs_airline_iata": "JL",
      "cs_flight_iata": "JL3",
      "counter": 114178
    },
    {
      "airline_iata": "MH",
      "airline_icao": "MAS",
      "flight_number": "9145",
      "flight_iata": "MH9145",
      "dep_iata": "JFK",
      "arr_iata": "HND",
      "dep_time": "13:35",
      "arr_time": "16:40",
      "dep_time_utc": "17:35",
      "arr_time_utc": "07:40",
      "duration": 845,
      "days": [
        "fri",
        "mon",
        "sat",
        "sun",
        "thu",
        "tue",
        "wed"
      ],
      "dep_terminal": "8",
      "arr_terminal": "3",
      "cs_airline_iata": "JL",
      "cs_flight_iata": "JL5",
      "counter": 13260
    },
    {
      "airline_iata": "NH",
      "airline_icao": "ANA",
      "flight_number": "109",
      "flight_iata": "NH109",
      "dep_iata": "JFK",
      "arr_iata": "HND",
      "dep_time": "13:30",
      "arr_time": "16:55",
      "dep_time_utc": "17:30",
      "arr_time_utc": "07:55",
      "duration": 865,
      "days": [
        "fri",
        "mon",
        "sat",
        "sun",
        "thu",
        "tue",
        "wed"
      ],
      "dep_terminal": "7",
      "arr_terminal": "2",
      "cs_airline_iata": null,
      "cs_flight_iata": null,
      "counter": 132115
    },
    {
      "airline_iata": "NH",
      "airline_icao": "ANA",
      "flight_number": "159",
      "flight_iata": "NH159",
      "dep_iata": "JFK",
      "arr_iata": "HND",
      "dep_time": "02:00",
      "arr_time": "05:15",
      "dep_time_utc": "06:00",
      "arr_time_utc": "20:15",
      "duration": 855,
      "days": [
        "fri",
        "mon",
        "sat",
        "sun",
        "thu",
        "tue",
        "wed"
      ],
      "dep_terminal": "7",
      "arr_terminal": "2",
      "cs_airline_iata": null,
      "cs_flight_iata": null,
      "counter": 263390
    },
    {
      "airline_iata": "SQ",
      "airline_icao": "SIA",
      "flight_number": "5915",
      "flight_iata": "SQ5915",
      "dep_iata": "JFK",
      "arr_iata": "HND",
      "dep_time": "13:30",
      "arr_time": "16:55",
      "dep_time_utc": "17:30",
      "arr_time_utc": "07:55",
      "duration": 865,
      "days": [
        "fri",
        "mon",
        "sat",
        "sun",
        "thu",
        "tue",
        "wed"
      ],
      "dep_terminal": "7",
      "arr_terminal": "2",
      "cs_airline_iata": "NH",
      "cs_flight_iata": "NH109",
      "counter": 132115
    },
    {
      "airline_iata": "TG",
      "airline_icao": "THA",
      "flight_number": "6173",
      "flight_iata": "TG6173",
      "dep_iata": "JFK",
      "arr_iata": "HND",
      "dep_time": "13:30",
      "arr_time": "16:55",
      "dep_time_utc": "17:30",
      "arr_time_utc": "07:55",
      "duration": 865,
      "days": [
        "fri",
        "mon",
        "sat",
        "sun",
        "thu",
        "tue",
        "wed"
      ],
      "dep_terminal": "7",
      "arr_terminal": "2",
      "cs_airline_iata": "NH",
      "cs_flight_iata": "NH109",
      "counter": 132115
    },
    {
      "airline_iata": "UA",
      "airline_icao": "UAL",
      "flight_number": "7909",
      "flight_iata": "UA7909",
      "dep_iata": "JFK",
      "arr_iata": "HND",
      "dep_time": "13:30",
      "arr_time": "16:55",
      "dep_time_utc": "17:30",
      "arr_time_utc": "07:55",
      "duration": 865,
      "days": [
        "fri",
        "mon",
        "sat",
        "sun",
        "thu",
        "tue",
        "wed"
      ],
      "dep_terminal": "7",
      "arr_terminal": "2",
      "cs_airline_iata": "NH",
      "cs_flight_iata": "NH109",
      "counter": 132115
    },
    {
      "airline_iata": "UA",
      "airline_icao": "UAL",
      "flight_number": "7923",
      "flight_iata": "UA7923",
      "dep_iata": "JFK",
      "arr_iata": "HND",
      "dep_time": "02:00",
      "arr_time": "05:15",
      "dep_time_utc": "06:00",
      "arr_time_utc": "20:15",
      "duration": 855,
      "days": [
        "fri",
        "mon",
        "sat",
        "sun",
        "thu",
        "tue",
        "wed"
      ],
      "dep_terminal": "7",
      "arr_terminal": "2",
      "cs_airline_iata": "NH",
      "cs_flight_iata": "NH159",
      "counter": 263031
    }
  ],
  "count": 16,
  "cached_at": 1779739985.4376152
}