{
  "dep_iata": "LHR",
  "arr_iata": "PEK",
  "routes": [
    {
      "airline_iata": "CA",
      "airline_icao": "CCA",
      "flight_number": "856",
      "flight_iata": "CA856",
      "dep_iata": "LHR",
      "arr_iata": "PEK",
      "dep_time": "22:40",
      "arr_time": "15:40",
      "dep_time_utc": "21:40",
      "arr_time_utc": "07:40",
      "duration": 600,
      "days": [
        "fri",
        "mon",
        "sat",
        "sun",
        "thu",
        "tue",
        "wed"
      ],
      "dep_terminal": "2",
      "arr_terminal": "3",
      "cs_airline_iata": null,
      "cs_flight_iata": null,
      "counter": 180359
    },
    {
      "airline_iata": "CA",
      "airline_icao": "CCA",
      "flight_number": "938",
      "flight_iata": "CA938",
      "dep_iata": "LHR",
      "arr_iata": "PEK",
      "dep_time": "20:25",
      "arr_time": "13:25",
      "dep_time_utc": "19:25",
      "arr_time_utc": "05:25",
      "duration": 600,
      "days": [
        "fri",
        "mon",
        "sat",
        "sun",
        "thu",
        "tue",
        "wed"
      ],
      "dep_terminal": "2",
      "arr_terminal": "3",
      "cs_airline_iata": null,
      "cs_flight_iata": null,
      "counter": 403885
    },
    {
      "airline_iata": "LA",
      "airline_icao": "LAN",
      "flight_number": "8780",
      "flight_iata": "LA8780",
      "dep_iata": "LHR",
      "arr_iata": "PEK",
      "dep_time": "20:25",
      "arr_time": "13:25",
      "dep_time_utc": "19:25",
      "arr_time_utc": "05:25",
      "duration": 600,
      "days": [
        "fri",
        "mon",
        "sat",
        "sun",
        "thu",
        "tue",
        "wed"
      ],
      "dep_terminal": "2",
      "arr_terminal": "3",
      "cs_airline_iata": "CA",
      "cs_flight_iata": "CA938",
      "counter": 103398
    },
    {
      "airline_iata": "TP",
      "airline_icao": "TAP",
      "flight_number": "8328",
      "flight_iata": "TP8328",
      "dep_iata": "LHR",
      "arr_iata": "PEK",
      "dep_time": "20:25",
      "arr_time": "13:25",
      "dep_time_utc": "19:25",
      "arr_time_utc": "05:25",
      "duration": 600,
      "days": [
        "fri",
        "mon",
        "sat",
        "sun",
        "thu",
        "tue",
        "wed"
      ],
      "dep_terminal": "2",
      "arr_terminal": "3",
      "cs_airline_iata": "CA",
      "cs_flight_iata": "CA938",
      "counter": 398721
    }
  ],
  "count": 4,
  "cached_at": 1779739994.31157
}