{
  "dep_iata": "PEK",
  "arr_iata": "HND",
  "routes": [
    {
      "airline_iata": "CA",
      "airline_icao": "CCA",
      "flight_number": "133",
      "flight_iata": "CA133",
      "dep_iata": "PEK",
      "arr_iata": "HND",
      "dep_time": "09:55",
      "arr_time": "14:30",
      "dep_time_utc": "01:55",
      "arr_time_utc": "05:30",
      "duration": 215,
      "days": [
        "fri",
        "mon",
        "sun",
        "thu",
        "tue",
        "wed"
      ],
      "dep_terminal": "3",
      "arr_terminal": "3",
      "cs_airline_iata": null,
      "cs_flight_iata": null,
      "counter": 98687
    },
    {
      "airline_iata": "CA",
      "airline_icao": "CCA",
      "flight_number": "133",
      "flight_iata": "CA133",
      "dep_iata": "PEK",
      "arr_iata": "HND",
      "dep_time": "10:00",
      "arr_time": "14:30",
      "dep_time_utc": "02:00",
      "arr_time_utc": "05:30",
      "duration": 210,
      "days": [
        "sat"
      ],
      "dep_terminal": "3",
      "arr_terminal": "3",
      "cs_airline_iata": null,
      "cs_flight_iata": null,
      "counter": 78032
    },
    {
      "airline_iata": "CA",
      "airline_icao": "CCA",
      "flight_number": "167",
      "flight_iata": "CA167",
      "dep_iata": "PEK",
      "arr_iata": "HND",
      "dep_time": "12:40",
      "arr_time": "17:30",
      "dep_time_utc": "04:40",
      "arr_time_utc": "08:30",
      "duration": 230,
      "days": [
        "sun"
      ],
      "dep_terminal": "3",
      "arr_terminal": "3",
      "cs_airline_iata": null,
      "cs_flight_iata": null,
      "counter": 42906
    },
    {
      "airline_iata": "CA",
      "airline_icao": "CCA",
      "flight_number": "167",
      "flight_iata": "CA167",
      "dep_iata": "PEK",
      "arr_iata": "HND",
      "dep_time": "12:50",
      "arr_time": "17:30",
      "dep_time_utc": "04:50",
      "arr_time_utc": "08:30",
      "duration": 220,
      "days": [
        "fri",
        "mon",
        "sat",
        "thu",
        "tue",
        "wed"
      ],
      "dep_terminal": "3",
      "arr_terminal": "3",
      "cs_airline_iata": null,
      "cs_flight_iata": null,
      "counter": 25947
    },
    {
      "airline_iata": "CA",
      "airline_icao": "CCA",
      "flight_number": "181",
      "flight_iata": "CA181",
      "dep_iata": "PEK",
      "arr_iata": "HND",
      "dep_time": "08:05",
      "arr_time": "12:25",
      "dep_time_utc": "00:05",
      "arr_time_utc": "03:25",
      "duration": 200,
      "days": [
        "fri",
        "mon",
        "sat",
        "sun",
        "thu",
        "tue",
        "wed"
      ],
      "dep_terminal": "3",
      "arr_terminal": "3",
      "cs_airline_iata": null,
      "cs_flight_iata": null,
      "counter": 106206
    },
    {
      "airline_iata": "CA",
      "airline_icao": "CCA",
      "flight_number": "183",
      "flight_iata": "CA183",
      "dep_iata": "PEK",
      "arr_iata": "HND",
      "dep_time": "17:10",
      "arr_time": "21:30",
      "dep_time_utc": "09:10",
      "arr_time_utc": "12:30",
      "duration": 200,
      "days": [
        "fri",
        "mon",
        "sat",
        "sun",
        "thu",
        "tue",
        "wed"
      ],
      "dep_terminal": "3",
      "arr_terminal": "3",
      "cs_airline_iata": null,
      "cs_flight_iata": null,
      "counter": 30945
    },
    {
      "airline_iata": "CA",
      "airline_icao": "CCA",
      "flight_number": "421",
      "flight_iata": "CA421",
      "dep_iata": "PEK",
      "arr_iata": "HND",
      "dep_time": "15:30",
      "arr_time": "20:00",
      "dep_time_utc": "07:30",
      "arr_time_utc": "11:00",
      "duration": 210,
      "days": [
        "fri",
        "mon",
        "sat",
        "sun",
        "thu",
        "tue",
        "wed"
      ],
      "dep_terminal": "3",
      "arr_terminal": "3",
      "cs_airline_iata": null,
      "cs_flight_iata": null,
      "counter": 103363
    },
    {
      "airline_iata": "CA",
      "airline_icao": "CCA",
      "flight_number": "6653",
      "flight_iata": "CA6653",
      "dep_iata": "PEK",
      "arr_iata": "HND",
      "dep_time": "08:20",
      "arr_time": "12:55",
      "dep_time_utc": "00:20",
      "arr_time_utc": "03:55",
      "duration": 215,
      "days": [
        "fri",
        "mon",
        "sat",
        "sun",
        "thu",
        "tue",
        "wed"
      ],
      "dep_terminal": "3",
      "arr_terminal": "2",
      "cs_airline_iata": "NH",
      "cs_flight_iata": "NH964",
      "counter": 144598
    },
    {
      "airline_iata": "CA",
      "airline_icao": "CCA",
      "flight_number": "6707",
      "flight_iata": "CA6707",
      "dep_iata": "PEK",
      "arr_iata": "HND",
      "dep_time": "15:10",
      "arr_time": "19:35",
      "dep_time_utc": "07:10",
      "arr_time_utc": "10:35",
      "duration": 205,
      "days": [
        "fri",
        "mon",
        "sat",
        "sun",
        "thu",
        "tue",
        "wed"
      ],
      "dep_terminal": "3",
      "arr_terminal": "3",
      "cs_airline_iata": "NH",
      "cs_flight_iata": "NH962",
      "counter": 156652
    },
    {
      "airline_iata": "CZ",
      "airline_icao": "CSN",
      "flight_number": "7802",
      "flight_iata": "CZ7802",
      "dep_iata": "PEK",
      "arr_iata": "HND",
      "dep_time": "16:20",
      "arr_time": "20:50",
      "dep_time_utc": "08:20",
      "arr_time_utc": "11:50",
      "duration": 210,
      "days": [
        "fri",
        "mon",
        "sat",
        "sun",
        "thu",
        "tue",
        "wed"
      ],
      "dep_terminal": "3",
      "arr_terminal": "3",
      "cs_airline_iata": "JL",
      "cs_flight_iata": "JL22",
      "counter": 143933
    },
    {
      "airline_iata": "CZ",
      "airline_icao": "CSN",
      "flight_number": "7804",
      "flight_iata": "CZ7804",
      "dep_iata": "PEK",
      "arr_iata": "HND",
      "dep_time": "08:25",
      "arr_time": "12:55",
      "dep_time_utc": "00:25",
      "arr_time_utc": "03:55",
      "duration": 210,
      "days": [
        "fri",
        "mon",
        "sat",
        "sun",
        "thu",
        "tue",
        "wed"
      ],
      "dep_terminal": "3",
      "arr_terminal": "3",
      "cs_airline_iata": "JL",
      "cs_flight_iata": "JL20",
      "counter": 146959
    },
    {
      "airline_iata": "JL",
      "airline_icao": "JAL",
      "flight_number": "20",
      "flight_iata": "JL20",
      "dep_iata": "PEK",
      "arr_iata": "HND",
      "dep_time": "08:25",
      "arr_time": "12:55",
      "dep_time_utc": "00:25",
      "arr_time_utc": "03:55",
      "duration": 210,
      "days": [
        "fri",
        "mon",
        "sat",
        "sun",
        "thu",
        "tue",
        "wed"
      ],
      "dep_terminal": "3",
      "arr_terminal": "3",
      "cs_airline_iata": null,
      "cs_flight_iata": null,
      "counter": 159232
    },
    {
      "airline_iata": "JL",
      "airline_icao": "JAL",
      "flight_number": "22",
      "flight_iata": "JL22",
      "dep_iata": "PEK",
      "arr_iata": "HND",
      "dep_time": "16:20",
      "arr_time": "20:50",
      "dep_time_utc": "08:20",
      "arr_time_utc": "11:50",
      "duration": 210,
      "days": [
        "fri",
        "mon",
        "sat",
        "sun",
        "thu",
        "tue",
        "wed"
      ],
      "dep_terminal": "3",
      "arr_terminal": "3",
      "cs_airline_iata": null,
      "cs_flight_iata": null,
      "counter": 156713
    },
    {
      "airline_iata": "MU",
      "airline_icao": "CES",
      "flight_number": "4200",
      "flight_iata": "MU4200",
      "dep_iata": "PEK",
      "arr_iata": "HND",
      "dep_time": "08:25",
      "arr_time": "12:55",
      "dep_time_utc": "00:25",
      "arr_time_utc": "03:55",
      "duration": 210,
      "days": [
        "fri",
        "mon",
        "sat",
        "sun",
        "thu",
        "tue",
        "wed"
      ],
      "dep_terminal": "3",
      "arr_terminal": "3",
      "cs_airline_iata": "JL",
      "cs_flight_iata": "JL20",
      "counter": 147813
    },
    {
      "airline_iata": "MU",
      "airline_icao": "CES",
      "flight_number": "4201",
      "flight_iata": "MU4201",
      "dep_iata": "PEK",
      "arr_iata": "HND",
      "dep_time": "16:20",
      "arr_time": "20:50",
      "dep_time_utc": "08:20",
      "arr_time_utc": "11:50",
      "duration": 210,
      "days": [
        "fri",
        "mon",
        "sat",
        "sun",
        "thu",
        "tue",
        "wed"
      ],
      "dep_terminal": "3",
      "arr_terminal": "3",
      "cs_airline_iata": "JL",
      "cs_flight_iata": "JL22",
      "counter": 144789
    },
    {
      "airline_iata": "NH",
      "airline_icao": "ANA",
      "flight_number": "5760",
      "flight_iata": "NH5760",
      "dep_iata": "PEK",
      "arr_iata": "HND",
      "dep_time": "12:40",
      "arr_time": "17:30",
      "dep_time_utc": "04:40",
      "arr_time_utc": "08:30",
      "duration": 230,
      "days": [
        "sun"
      ],
      "dep_terminal": "3",
      "arr_terminal": "3",
      "cs_airline_iata": "CA",
      "cs_flight_iata": "CA167",
      "counter": 7695
    },
    {
      "airline_iata": "NH",
      "airline_icao": "ANA",
      "flight_number": "5760",
      "flight_iata": "NH5760",
      "dep_iata": "PEK",
      "arr_iata": "HND",
      "dep_time": "12:50",
      "arr_time": "17:30",
      "dep_time_utc": "04:50",
      "arr_time_utc": "08:30",
      "duration": 220,
      "days": [
        "fri",
        "mon",
        "sat",
        "thu",
        "tue",
        "wed"
      ],
      "dep_terminal": "3",
      "arr_terminal": "3",
      "cs_airline_iata": "CA",
      "cs_flight_iata": "CA167",
      "counter": 21377
    },
    {
      "airline_iata": "NH",
      "airline_icao": "ANA",
      "flight_number": "962",
      "flight_iata": "NH962",
      "dep_iata": "PEK",
      "arr_iata": "HND",
      "dep_time": "15:10",
      "arr_time": "19:35",
      "dep_time_utc": "07:10",
      "arr_time_utc": "10:35",
      "duration": 205,
      "days": [
        "fri",
        "mon",
        "sat",
        "sun",
        "thu",
        "tue",
        "wed"
      ],
      "dep_terminal": "3",
      "arr_terminal": "3",
      "cs_airline_iata": null,
      "cs_flight_iata": null,
      "counter": 156645
    },
    {
      "airline_iata": "NH",
      "airline_icao": "ANA",
      "flight_number": "964",
      "flight_iata": "NH964",
      "dep_iata": "PEK",
      "arr_iata": "HND",
      "dep_time": "08:20",
      "arr_time": "12:55",
      "dep_time_utc": "00:20",
      "arr_time_utc": "03:55",
      "duration": 215,
      "days": [
        "fri",
        "mon",
        "sat",
        "sun",
        "thu",
        "tue",
        "wed"
      ],
      "dep_terminal": "3",
      "arr_terminal": "2",
      "cs_airline_iata": null,
      "cs_flight_iata": null,
      "counter": 144600
    },
    {
      "airline_iata": "SC",
      "airline_icao": "CDG",
      "flight_number": "111",
      "flight_iata": "SC111",
      "dep_iata": "PEK",
      "arr_iata": "HND",
      "dep_time": "09:55",
      "arr_time": "14:30",
      "dep_time_utc": "01:55",
      "arr_time_utc": "05:30",
      "duration": 215,
      "days": [
        "fri",
        "mon",
        "sun",
        "thu",
        "tue",
        "wed"
      ],
      "dep_terminal": "3",
      "arr_terminal": "3",
      "cs_airline_iata": "CA",
      "cs_flight_iata": "CA133",
      "counter": 12078
    },
    {
      "airline_iata": "SC",
      "airline_icao": "CDG",
      "flight_number": "111",
      "flight_iata": "SC111",
      "dep_iata": "PEK",
      "arr_iata": "HND",
      "dep_time": "10:00",
      "arr_time": "14:30",
      "dep_time_utc": "02:00",
      "arr_time_utc": "05:30",
      "duration": 210,
      "days": [
        "sat"
      ],
      "dep_terminal": "3",
      "arr_terminal": "3",
      "cs_airline_iata": "CA",
      "cs_flight_iata": "CA133",
      "counter": 2456
    }
  ],
  "count": 21,
  "cached_at": 1779734588.725579
}