{
  "dep_iata": "PEK",
  "arr_iata": "DXB",
  "routes": [
    {
      "airline_iata": "EK",
      "airline_icao": "UAE",
      "flight_number": "307",
      "flight_iata": "EK307",
      "dep_iata": "PEK",
      "arr_iata": "DXB",
      "dep_time": "00:40",
      "arr_time": "05:00",
      "dep_time_utc": "16:40",
      "arr_time_utc": "01:00",
      "duration": 500,
      "days": [
        "fri",
        "mon",
        "sat",
        "sun",
        "thu",
        "tue",
        "wed"
      ],
      "dep_terminal": "3",
      "arr_terminal": "3",
      "cs_airline_iata": null,
      "cs_flight_iata": null,
      "counter": 279535
    }
  ],
  "count": 1,
  "cached_at": 1779734593.387071
}